Metadata-Version: 2.1
Name: ts-eval
Version: 0.2.3
Summary: Time Series analysis and evaluation tools
Home-page: https://github.com/vshulyak/ts-eval
Author: Vladimir Shulyak
Author-email: vladimir@shulyak.net
License: UNKNOWN
Platform: UNKNOWN
Classifier: Development Status :: 4 - Beta
Classifier: Programming Language :: Python :: 3.6
Classifier: Programming Language :: Python :: 3.7
Classifier: Programming Language :: Python :: 3.8
Classifier: License :: OSI Approved :: MIT License
Classifier: Operating System :: OS Independent
Requires-Dist: pandas (>=0.23.0)
Requires-Dist: numpy (>=1.16.0)
Requires-Dist: xarray (>=0.13)
Requires-Dist: scipy (>=1.3)
Requires-Dist: statsmodels (>=0.10)
Requires-Dist: jupyterlab (>=1.1)
Requires-Dist: matplotlib (>=3.0)
Requires-Dist: dataclasses
Requires-Dist: ipykernel
Requires-Dist: jupyter-contrib-nbextensions
Provides-Extra: debug
Requires-Dist: pdbpp ; extra == 'debug'
Provides-Extra: dev
Requires-Dist: hypothesis[numpy] ; extra == 'dev'
Requires-Dist: pytest ; extra == 'dev'
Requires-Dist: tox ; extra == 'dev'
Requires-Dist: pre-commit ; extra == 'dev'
Requires-Dist: coverage ; extra == 'dev'
Requires-Dist: twine ; extra == 'dev'
Requires-Dist: pdbpp ; extra == 'dev'
Requires-Dist: holidays (>=0.9) ; extra == 'dev'
Provides-Extra: extra_runtime_libs
Requires-Dist: holidays (>=0.9) ; extra == 'extra_runtime_libs'
Provides-Extra: pypi
Requires-Dist: twine ; extra == 'pypi'
Provides-Extra: tests
Requires-Dist: hypothesis[numpy] ; extra == 'tests'
Requires-Dist: pytest ; extra == 'tests'
Requires-Dist: tox ; extra == 'tests'
Requires-Dist: pre-commit ; extra == 'tests'
Requires-Dist: coverage ; extra == 'tests'
Provides-Extra: tests_and_extra_runtime_libs
Requires-Dist: hypothesis[numpy] ; extra == 'tests_and_extra_runtime_libs'
Requires-Dist: pytest ; extra == 'tests_and_extra_runtime_libs'
Requires-Dist: tox ; extra == 'tests_and_extra_runtime_libs'
Requires-Dist: pre-commit ; extra == 'tests_and_extra_runtime_libs'
Requires-Dist: coverage ; extra == 'tests_and_extra_runtime_libs'
Requires-Dist: holidays (>=0.9) ; extra == 'tests_and_extra_runtime_libs'
